lib_bgp_data/__init__.py
lib_bgp_data/__main__.py
lib_bgp_data/conftest.py
lib_bgp_data/api/__init__.py
lib_bgp_data/api/api_utils.py
lib_bgp_data/api/averages.py
lib_bgp_data/api/extrapolator_engine_results.py
lib_bgp_data/api/hijacks.py
lib_bgp_data/api/policies.py
lib_bgp_data/api/relationships.py
lib_bgp_data/api/roas.py
lib_bgp_data/api/rpki_validity_results.py
lib_bgp_data/base_classes/__init__.py
lib_bgp_data/base_classes/decometa.py
lib_bgp_data/base_classes/enumerable_enum.py
lib_bgp_data/base_classes/file.py
lib_bgp_data/base_classes/parser.py
lib_bgp_data/base_classes/tests/__init__.py
lib_bgp_data/base_classes/tests/test_enumerable_enum.py
lib_bgp_data/base_classes/tests/test_file.py
lib_bgp_data/base_classes/tests/test_parser.py
lib_bgp_data/bgpstream_website_parser/__init__.py
lib_bgp_data/bgpstream_website_parser/bgpstream_website_parser.py
lib_bgp_data/bgpstream_website_parser/data_classes.py
lib_bgp_data/bgpstream_website_parser/event_types.py
lib_bgp_data/bgpstream_website_parser/tables.py
lib_bgp_data/bgpstream_website_parser/tests/__init__.py
lib_bgp_data/bgpstream_website_parser/tests/test_bgpstream_website_parser.py
lib_bgp_data/bgpstream_website_parser/tests/test_data_classes.py
lib_bgp_data/bgpstream_website_parser/tests/test_tables.py
lib_bgp_data/database/__init__.py
lib_bgp_data/database/config.py
lib_bgp_data/database/database.py
lib_bgp_data/database/generic_table.py
lib_bgp_data/database/generic_table_test.py
lib_bgp_data/database/postgres.py
lib_bgp_data/database/tests/__init__.py
lib_bgp_data/database/tests/generic_table_test.py
lib_bgp_data/database/tests/test_config.py
lib_bgp_data/database/tests/test_database.py
lib_bgp_data/database/tests/test_generic_table.py
lib_bgp_data/database/tests/test_multi_install.py
lib_bgp_data/database/tests/test_postgres.py
lib_bgp_data/extrapolator/__init__.py
lib_bgp_data/extrapolator/extrapolator.py
lib_bgp_data/extrapolator/tables.py
lib_bgp_data/extrapolator/tests/__init__.py
lib_bgp_data-0.3.0.dist-info/AUTHORS
lib_bgp_data-0.3.0.dist-info/METADATA
lib_bgp_data-0.3.0.dist-info/WHEEL
lib_bgp_data-0.3.0.dist-info/entry_points.txt
lib_bgp_data-0.3.0.dist-info/top_level.txt
lib_bgp_data-0.3.0.dist-info/RECORD
